conxugador/__init__.py
conxugador/__main__.py
conxugador/conjugation.py
conxugador/load_paradigms.py
conxugador/verbos.txt
conxugador-2021.4.dist-info/LICENSE
conxugador-2021.4.dist-info/METADATA
conxugador-2021.4.dist-info/WHEEL
conxugador-2021.4.dist-info/entry_points.txt
conxugador-2021.4.dist-info/top_level.txt
conxugador-2021.4.dist-info/RECORD
