Metadata-Version: 2.1
Name: conxugador
Version: 2021.4
Summary: This tool conjugates Galician verbs
Home-page: https://gitlab.com/avieites/conxugador
Author: Andrés Vieites
Author-email: andres@vieites.gal
License: GNU GPLv3
Project-URL: PyPI, https://pypi.org/project/conxugador/
Platform: UNKNOWN
Classifier: License :: OSI Approved :: GNU General Public License v3 (GPLv3)
Classifier: Environment :: Console
Classifier: Intended Audience :: Education
Classifier: Intended Audience :: Science/Research
Classifier: Natural Language :: Galician
Classifier: Operating System :: OS Independent
Classifier: Programming Language :: Python :: 3
Requires-Python: >=3.6
